debiaiServer/__init__.py
debiaiServer/init.py
debiaiServer/server.py
debiaiServer/swagger.yaml
debiaiServer/websrv.py
debiaiServer/config/__init__.py
debiaiServer/config/init_config.py
debiaiServer/controller/__init__.py
debiaiServer/controller/algoProviders.py
debiaiServer/controller/data.py
debiaiServer/controller/dataProviders.py
debiaiServer/controller/exportMethods.py
debiaiServer/controller/layouts.py
debiaiServer/controller/models.py
debiaiServer/controller/projects.py
debiaiServer/controller/pythonModuleDp.py
debiaiServer/controller/selection.py
debiaiServer/controller/statisticalOperations.py
debiaiServer/controller/widgetConfigurations.py
debiaiServer/modules/__init__.py
debiaiServer/modules/algoProviders/AlgoProvider.py
debiaiServer/modules/algoProviders/AlgoProviderException.py
debiaiServer/modules/algoProviders/__init__.py
debiaiServer/modules/algoProviders/algoProvidersManager.py
debiaiServer/modules/algoProviders/integratedAlgoProvider/__init__.py
debiaiServer/modules/algoProviders/integratedAlgoProvider/integratedAlgoProvider.py
debiaiServer/modules/algoProviders/integratedAlgoProvider/utils.py
debiaiServer/modules/algoProviders/integratedAlgoProvider/algorithms/__init__.py
debiaiServer/modules/algoProviders/integratedAlgoProvider/algorithms/classificationErrorMetric.py
debiaiServer/modules/algoProviders/integratedAlgoProvider/algorithms/regressionErrorMetric.py
debiaiServer/modules/dataProviders/DataProvider.py
debiaiServer/modules/dataProviders/DataProviderException.py
debiaiServer/modules/dataProviders/__init__.py
debiaiServer/modules/dataProviders/dataProviderManager.py
debiaiServer/modules/dataProviders/pythonDataProvider/PythonDataProvider.py
debiaiServer/modules/dataProviders/pythonDataProvider/__init__.py
debiaiServer/modules/dataProviders/pythonDataProvider/dataUtils/__init__.py
debiaiServer/modules/dataProviders/pythonDataProvider/dataUtils/hash.py
debiaiServer/modules/dataProviders/pythonDataProvider/dataUtils/models.py
debiai_server-0.1.0.dist-info/LICENSE
debiai_server-0.1.0.dist-info/METADATA
debiai_server-0.1.0.dist-info/WHEEL
debiai_server-0.1.0.dist-info/entry_points.txt
debiai_server-0.1.0.dist-info/top_level.txt
debiai_server-0.1.0.dist-info/RECORD
